LICENSE
contourheightmap/__init__.py
contourheightmap/cli.py
contourheightmap-1.1.1.dist-info/entry_points.txt
contourheightmap-1.1.1.dist-info/LICENSE
contourheightmap-1.1.1.dist-info/WHEEL
contourheightmap-1.1.1.dist-info/METADATA
contourheightmap-1.1.1.dist-info/RECORD
