Metadata-Version: 2.1
Name: contourheightmap
Version: 1.1.1
Summary: A fast python library and command line tool for generating topographic contour maps from heightmaps and images.
Home-page: https://gitlab.com/dodgyville/contourheightmap
License: LGPLv3
Author: Luke Miller
Author-email: dodgyville@gmail.com
Requires-Python: >=3.8,<4.0
Classifier: License :: Other/Proprietary License
Classifier: Programming Language :: Python :: 3
Classifier: Programming Language :: Python :: 3.10
Classifier: Programming Language :: Python :: 3.8
Classifier: Programming Language :: Python :: 3.9
Requires-Dist: Pillow (>=9.1.0,<10.0.0)
Requires-Dist: importlib (>=1.0.4,<2.0.0)
Requires-Dist: matplotlib (>=3.5.1,<4.0.0)
Requires-Dist: numpy (>=1.22.3,<2.0.0)
Requires-Dist: typer (>=0.4.1,<0.5.0)
Project-URL: Repository, https://gitlab.com/dodgyville/contourheightmap
